linux_utils/__init__.py
linux_utils/atomic.py
linux_utils/cli.py
linux_utils/crypttab.py
linux_utils/fstab.py
linux_utils/luks.py
linux_utils/network.py
linux_utils/tabfile.py
linux_utils/tests.py
linux_utils-0.7.dist-info/LICENSE.txt
linux_utils-0.7.dist-info/METADATA
linux_utils-0.7.dist-info/WHEEL
linux_utils-0.7.dist-info/entry_points.txt
linux_utils-0.7.dist-info/top_level.txt
linux_utils-0.7.dist-info/RECORD
